{"Resources":{"Info":{"Number of Resources":3,"Load Resources":true},"Resource 0":{"UUID & UUID Directory":637662830,"Type":2,"Name":"Baker_house.png","PathAssets":"E:\\Andreu\\Repository\\czx\\TempMotor3D_P3\\Engine\\Game\\Assets\\Baker_house.png"},"Resource 1":{"UUID & UUID Directory":1707514829,"Type":3,"Name":"Baker_house","PathAssets":"E:\\Andreu\\Repository\\czx\\TempMotor3D_P3\\Engine\\Game\\Assets\\BakerHouse.fbx"},"Resource 2":{"UUID & UUID Directory":1887527748,"Type":3,"Name":"Chimney","PathAssets":"E:\\Andreu\\Repository\\czx\\TempMotor3D_P3\\Engine\\Game\\Assets\\BakerHouse.fbx"}}}