{"particlestate":{"texture":{"texture_path":"spark1.png","columns":1,"rows":1,"numberOfFrames":1,"AnimationOrder":0},"initial_state":{"force":{"x":20,"y":20,"z":0},"forceVariation":{"x":50,"y":50,"z":0},"Size":3,"SizeVariation":0,"RGBATint":{"x":1,"y":1,"z":1,"w":1},"RGBATintVariation":{"x":0,"y":0,"z":0,"w":0},"alpha_preview":true,"alpha_half_preview":false,"options_menu":true,"alpha":true,"alpha_bar":true,"side_preview":true,"inputs_mode":2,"picker_mode":0},"final_state":{"force":{"x":-20,"y":20,"z":0},"forceVariation":{"x":20,"y":50,"z":0},"Size":1,"SizeVariation":0,"RGBATint":{"x":1,"y":1,"z":1,"w":0.78823530673980713},"RGBATintVariation":{"x":0,"y":0,"z":0,"w":0},"alpha_preview":true,"alpha_half_preview":false,"options_menu":true,"alpha":true,"alpha_bar":true,"side_preview":true,"inputs_mode":2,"picker_mode":0}}}