{"particlestate":{"texture":{"texture_path":"fire_wall.png","columns":9,"rows":9,"numberOfFrames":81,"AnimationOrder":0},"initial_state":{"force":{"x":0,"y":0,"z":0},"forceVariation":{"x":0,"y":0,"z":0},"Size":20,"SizeVariation":0,"RGBATint":{"x":1,"y":1,"z":1,"w":1},"RGBATintVariation":{"x":0,"y":0,"z":0,"w":0},"alpha_preview":true,"alpha_half_preview":false,"options_menu":true,"alpha":true,"alpha_bar":true,"side_preview":true,"inputs_mode":2,"picker_mode":0},"final_state":{"force":{"x":0,"y":0,"z":0},"forceVariation":{"x":0,"y":0,"z":0},"Size":20,"SizeVariation":0,"RGBATint":{"x":1,"y":1,"z":1,"w":0.93333333730697632},"RGBATintVariation":{"x":0,"y":0,"z":0,"w":0},"alpha_preview":true,"alpha_half_preview":false,"options_menu":true,"alpha":true,"alpha_bar":true,"side_preview":true,"inputs_mode":2,"picker_mode":0}}}