{"Prefab":{"Info":{"Number of GameObjects":25,"Directory Prefab":"C:\\Users\\mizqu\\Documents\\GitHub\\CulverinEngine-Project3\\Engine\\Game\\Assets\\Barrel8Pack_Box.fbx","Resources":{"Number of Resources":9,"Last Write":1521746309,"Resource 0":{"UUID Resource":1856916284,"Name":"Barrel4Pack:Barrel4Pack:Barrel4PackBase:polySurface1"},"Resource 1":{"UUID Resource":1543604439,"Name":"Barrel4Pack:Barrel4Pack:Barrel4PackBase:polySurface2"},"Resource 2":{"UUID Resource":1934678323,"Name":"Barrel4Pack:Barrel4Pack:Barrel4PackBase:polySurface3"},"Resource 3":{"UUID Resource":320297121,"Name":"Barrel4Pack:Barrel4Pack:Barrel4PackBase:polySurface4"},"Resource 4":{"UUID Resource":1888905849,"Name":"Barrel4Pack:Barrel4Pack:Barrel4PackBase:polySurface5"},"Resource 5":{"UUID Resource":1036353401,"Name":"Barrel4Pack:Barrel4Pack:Barrel4PackBase:polySurface6"},"Resource 6":{"UUID Resource":1680953332,"Name":"Barrel4Pack:Barrel4Pack:Barrel4PackBase:polySurface7"},"Resource 7":{"UUID Resource":547048260,"Name":"Barrel4Pack:Barrel4Pack:Barrel4PackBase:polySurface8"},"Resource 8":{"UUID Resource":1554620429,"Name":"Barrel4Pack:Barrel4Pack:Barrel4PackBase:pCube17"}}},"GameObject0":{"UUID":415601429,"Parent":-1,"Name":"Barrel8Pack_Box.fbx","Tag":"undefined","Number of Components":1,"Components":{"Component 0":{"Component:":"Transform","Type":0,"Position":[0,0,0],"Rotation":[0,0,0,1],"Scale":[1,1,1]}}},"GameObject1":{"UUID":1539912378,"Parent":415601429,"Name":"Barrel4Pack:Barrel4Pack:Barrel4PackBase:Cylinder018_$AssimpFbx$_Translation","Number of Components":1,"Components":{"Component 0":{"Component:":"Transform","Type":0,"Position":[-9.9098062515258789,1085.5404052734375,-383.14492797851563],"Rotation":[0,0,0,1],"Scale":[1,1,1]}}},"GameObject2":{"UUID":1413559557,"Parent":1539912378,"Name":"Barrel4Pack:Barrel4Pack:Barrel4PackBase:Cylinder018_$AssimpFbx$_RotationOffset","Number of Components":1,"Components":{"Component 0":{"Component:":"Transform","Type":0,"Position":[327.47451782226563,1.3195917745179031e-06,-307.65460205078125],"Rotation":[0,0,0,1],"Scale":[1,1,1]}}},"GameObject3":{"UUID":696826828,"Parent":1413559557,"Name":"Barrel4Pack:Barrel4Pack:Barrel4PackBase:Cylinder018_$AssimpFbx$_RotationPivot","Number of Components":1,"Components":{"Component 0":{"Component:":"Transform","Type":0,"Position":[-317.5645751953125,-320.54037475585938,-9.9099521636962891],"Rotation":[0,0,0,1],"Scale":[1,1,1]}}},"GameObject4":{"UUID":2125006458,"Parent":696826828,"Name":"Barrel4Pack:Barrel4Pack:Barrel4PackBase:Cylinder018_$AssimpFbx$_Rotation","Number of Components":1,"Components":{"Component 0":{"Component:":"Transform","Type":0,"Position":[0,0,0],"Rotation":[-0.5,0.50000005960464478,0.5,-0.49999994039535522],"Scale":[1,1,1]}}},"GameObject5":{"UUID":631203294,"Parent":2125006458,"Name":"Barrel4Pack:Barrel4Pack:Barrel4PackBase:Cylinder018_$AssimpFbx$_RotationPivotInverse","Number of Components":1,"Components":{"Component 0":{"Component:":"Transform","Type":0,"Position":[317.5645751953125,320.54037475585938,9.9099521636962891],"Rotation":[0,0,0,1],"Scale":[1,1,1]}}},"GameObject6":{"UUID":1046663013,"Parent":631203294,"Name":"Barrel4Pack:Barrel4Pack:Barrel4PackBase:Cylinder018_$AssimpFbx$_ScalingOffset","Number of Components":1,"Components":{"Component 0":{"Component:":"Transform","Type":0,"Position":[-316.06100463867188,-319.022705078125,-9.870936393737793],"Rotation":[0,0,0,1],"Scale":[1,1,1]}}},"GameObject7":{"UUID":1310518069,"Parent":1046663013,"Name":"Barrel4Pack:Barrel4Pack:Barrel4PackBase:Cylinder018_$AssimpFbx$_ScalingPivot","Number of Components":1,"Components":{"Component 0":{"Component:":"Transform","Type":0,"Position":[-1.5035748481750488,-1.5176644325256348,-0.03901556134223938],"Rotation":[0,0,0,1],"Scale":[1,1,1]}}},"GameObject8":{"UUID":1588255407,"Parent":1310518069,"Name":"Barrel4Pack:Barrel4Pack:Barrel4PackBase:Cylinder018_$AssimpFbx$_Scaling","Number of Components":1,"Components":{"Component 0":{"Component:":"Transform","Type":0,"Position":[0,0,0],"Rotation":[0,0,0,1],"Scale":[233.70637512207031,233.70637512207031,281.05886840820313]}}},"GameObject9":{"UUID":1996706717,"Parent":1588255407,"Name":"Barrel4Pack:Barrel4Pack:Barrel4PackBase:Cylinder018_$AssimpFbx$_ScalingPivotInverse","Number of Components":1,"Components":{"Component 0":{"Component:":"Transform","Type":0,"Position":[1.5035748481750488,1.5176644325256348,0.03901556134223938],"Rotation":[0,0,0,1],"Scale":[1,1,1]}}},"GameObject10":{"UUID":1806906653,"Parent":1996706717,"Name":"Barrel4Pack:Barrel4Pack:Barrel4PackBase:Cylinder018","Number of Components":1,"Components":{"Component 0":{"Component:":"Transform","Type":0,"Position":[0,0,0],"Rotation":[0,0,0,1],"Scale":[1,1,1]}}},"GameObject11":{"UUID":1203530900,"Parent":1806906653,"Name":"Barrel4Pack:Barrel4Pack:Barrel4PackBase:polySurface1","Number of Components":3,"Components":{"Component 0":{"Component:":"Transform","Type":0,"Position":[0,0,0],"Rotation":[0,0,0,1],"Scale":[1,1,1]},"Component 1":{"Component:":"CompMesh","Type":2,"UUID":507850254,"Resource Mesh UUID":1856916284,"Has Skeleton":false,"Generated Skeleton":false},"Component 2":{"Component:":"CompMaterial","Type":3,"Color":[1,1,1,1],"UUID":871769526,"MaterialName:":"barrel"}}},"GameObject12":{"UUID":1283338132,"Parent":1806906653,"Name":"Barrel4Pack:Barrel4Pack:Barrel4PackBase:polySurface2","Number of Components":3,"Components":{"Component 0":{"Component:":"Transform","Type":0,"Position":[-3.0071496963500977,-2.0678584712607861e-12,-6.7463368225162412e-08],"Rotation":[0,0,0,1],"Scale":[1,1,1]},"Component 1":{"Component:":"CompMesh","Type":2,"UUID":1226954537,"Resource Mesh UUID":1543604439,"Has Skeleton":false,"Generated Skeleton":false},"Component 2":{"Component:":"CompMaterial","Type":3,"Color":[1,1,1,1],"UUID":1344793758,"MaterialName:":"barrel"}}},"GameObject13":{"UUID":2041667459,"Parent":1806906653,"Name":"Barrel4Pack:Barrel4Pack:Barrel4PackBase:polySurface3","Number of Components":3,"Components":{"Component 0":{"Component:":"Transform","Type":0,"Position":[-3.0071496963500977,2.1031987262887242e-09,-0.078031048178672791],"Rotation":[1,0,0,-4.3711388286737929e-08],"Scale":[1,1,1]},"Component 1":{"Component:":"CompMesh","Type":2,"UUID":987568109,"Resource Mesh UUID":1934678323,"Has Skeleton":false,"Generated Skeleton":false},"Component 2":{"Component:":"CompMaterial","Type":3,"Color":[1,1,1,1],"UUID":1642874337,"MaterialName:":"barrel"}}},"GameObject14":{"UUID":1427693410,"Parent":1806906653,"Name":"Barrel4Pack:Barrel4Pack:Barrel4PackBase:polySurface4","Number of Components":3,"Components":{"Component 0":{"Component:":"Transform","Type":0,"Position":[-2.1052652954267614e-09,2.1052664056497861e-09,-0.078030981123447418],"Rotation":[1,0,0,-4.3711388286737929e-08],"Scale":[1,1,1]},"Component 1":{"Component:":"CompMesh","Type":2,"UUID":1162296215,"Resource Mesh UUID":320297121,"Has Skeleton":false,"Generated Skeleton":false},"Component 2":{"Component:":"CompMaterial","Type":3,"Color":[1,1,1,1],"UUID":893481908,"MaterialName:":"barrel"}}},"GameObject15":{"UUID":1092597866,"Parent":1806906653,"Name":"Barrel4Pack:Barrel4Pack:Barrel4PackBase:polySurface5","Number of Components":3,"Components":{"Component 0":{"Component:":"Transform","Type":0,"Position":[1.8902386166724794e-12,3,-6.8491274873849761e-08],"Rotation":[0,0,0,1],"Scale":[1,1,1]},"Component 1":{"Component:":"CompMesh","Type":2,"UUID":1737768399,"Resource Mesh UUID":1888905849,"Has Skeleton":false,"Generated Skeleton":false},"Component 2":{"Component:":"CompMaterial","Type":3,"Color":[1,1,1,1],"UUID":240002093,"MaterialName:":"barrel"}}},"GameObject16":{"UUID":1762943093,"Parent":1806906653,"Name":"Barrel4Pack:Barrel4Pack:Barrel4PackBase:polySurface6","Number of Components":3,"Components":{"Component 0":{"Component:":"Transform","Type":0,"Position":[-3.0071496963500977,3,-1.3595465020443953e-07],"Rotation":[0,0,0,1],"Scale":[1,1,1]},"Component 1":{"Component:":"CompMesh","Type":2,"UUID":580717115,"Resource Mesh UUID":1036353401,"Has Skeleton":false,"Generated Skeleton":false},"Component 2":{"Component:":"CompMaterial","Type":3,"Color":[1,1,1,1],"UUID":1579124993,"MaterialName:":"barrel"}}},"GameObject17":{"UUID":1983313135,"Parent":1806906653,"Name":"Barrel4Pack:Barrel4Pack:Barrel4PackBase:polySurface7","Number of Components":3,"Components":{"Component 0":{"Component:":"Transform","Type":0,"Position":[-3.0071496963500977,3,-0.07803112268447876],"Rotation":[1,0,0,-4.3711388286737929e-08],"Scale":[1,1,1]},"Component 1":{"Component:":"CompMesh","Type":2,"UUID":1340237029,"Resource Mesh UUID":1680953332,"Has Skeleton":false,"Generated Skeleton":false},"Component 2":{"Component:":"CompMaterial","Type":3,"Color":[1,1,1,1],"UUID":477733859,"MaterialName:":"barrel"}}},"GameObject18":{"UUID":82272703,"Parent":1806906653,"Name":"Barrel4Pack:Barrel4Pack:Barrel4PackBase:polySurface8","Number of Components":3,"Components":{"Component 0":{"Component:":"Transform","Type":0,"Position":[-2.10282613544166e-09,3,-0.078031055629253387],"Rotation":[1,0,0,-4.3711388286737929e-08],"Scale":[1,1,1]},"Component 1":{"Component:":"CompMesh","Type":2,"UUID":568969014,"Resource Mesh UUID":547048260,"Has Skeleton":false,"Generated Skeleton":false},"Component 2":{"Component:":"CompMaterial","Type":3,"Color":[1,1,1,1],"UUID":1855854779,"MaterialName:":"barrel"}}},"GameObject19":{"UUID":964463357,"Parent":415601429,"Name":"Barrel4Pack:Barrel4Pack:Barrel4PackBase:pCube17_$AssimpFbx$_RotationOffset","Number of Components":1,"Components":{"Component 0":{"Component:":"Transform","Type":0,"Position":[1.3442899408650649e-13,45,-1.2140936860305374e-06],"Rotation":[0,0,0,1],"Scale":[1,1,1]}}},"GameObject20":{"UUID":1532186948,"Parent":964463357,"Name":"Barrel4Pack:Barrel4Pack:Barrel4PackBase:pCube17_$AssimpFbx$_RotationPivot","Number of Components":1,"Components":{"Component 0":{"Component:":"Transform","Type":0,"Position":[3.825447987895747e-13,789.0218505859375,-2.4281996502395486e-06],"Rotation":[0,0,0,1],"Scale":[1,1,1]}}},"GameObject21":{"UUID":432309277,"Parent":1532186948,"Name":"Barrel4Pack:Barrel4Pack:Barrel4PackBase:pCube17_$AssimpFbx$_RotationPivotInverse","Number of Components":1,"Components":{"Component 0":{"Component:":"Transform","Type":0,"Position":[-3.825447987895747e-13,-789.0218505859375,2.4281996502395486e-06],"Rotation":[0,0,0,1],"Scale":[1,1,1]}}},"GameObject22":{"UUID":820861312,"Parent":432309277,"Name":"Barrel4Pack:Barrel4Pack:Barrel4PackBase:pCube17_$AssimpFbx$_ScalingPivot","Number of Components":1,"Components":{"Component 0":{"Component:":"Transform","Type":0,"Position":[3.825447987895747e-13,789.0218505859375,-2.4281996502395486e-06],"Rotation":[0,0,0,1],"Scale":[1,1,1]}}},"GameObject23":{"UUID":350588788,"Parent":820861312,"Name":"Barrel4Pack:Barrel4Pack:Barrel4PackBase:pCube17_$AssimpFbx$_ScalingPivotInverse","Number of Components":1,"Components":{"Component 0":{"Component:":"Transform","Type":0,"Position":[-3.825447987895747e-13,-789.0218505859375,2.4281996502395486e-06],"Rotation":[0,0,0,1],"Scale":[1,1,1]}}},"GameObject24":{"UUID":42877546,"Parent":350588788,"Name":"Barrel4Pack:Barrel4Pack:Barrel4PackBase:pCube17","Number of Components":3,"Components":{"Component 0":{"Component:":"Transform","Type":0,"Position":[0,0,0],"Rotation":[0,0,0,1],"Scale":[1,1,1]},"Component 1":{"Component:":"CompMesh","Type":2,"UUID":175360736,"Resource Mesh UUID":1554620429,"Has Skeleton":false,"Generated Skeleton":false},"Component 2":{"Component:":"CompMaterial","Type":3,"Color":[1,1,1,1],"UUID":345267861,"MaterialName:":"BarrelBox_Color"}}}}}