{"Prefab":{"Info":{"Number of GameObjects":1,"Directory Prefab":"","Resources":{"Number of Resources":0,"Type":3}},"GameObject0":{"UUID":843564124,"Parent":-1,"Name":"Particle_MetalCollision","Tag":"undefined","AnimRotations":true,"AnimScales":false,"AnimTranslations":false,"Number of Components":3,"Components":{"Component 0":{"Component:":"Transform","Type":0,"Position":[90.899993896484375,8,316.49996948242188],"Rotation":[-0.5,-0.5,-0.50000005960464478,0.50000005960464478],"Scale":[1,1,1]},"Component 1":{"Component:":"CompParticleSystem","Type":21,"ParticleResource:":"Particle_MetalCollision_particle","EmitterResource:":"Particle_MetalCollision_emitter","Preview:":true,"Active:":false,"DiscardDistance":100},"Component 2":{"Component:":"Script","Type":8,"UUID":645383409,"Name Script":"ParticleManager","Resource Script UUID":1054898412,"Number of Variables: ":3,"Variables":{"Variable 0":{"Type: ":"float","Value: ":1,"Name: ":"duration"},"Variable 1":{"Type: ":"float","Value: ":0,"Name: ":"timer"},"Variable 2":{"Type: ":"unknown","Value: ":"unknown","Name: ":"particles"}}}}}}}