{
  "Input": {
    "Directory": "player_action",
    "InputManager": { "Size": 1 },
    "InputManager0": {
      "InputManagerActionSize": 12,
      "InputManagerName": "Player",
      "InputManagerActive": true,
      "InputManagerBlock": false,
      "InputAction0": {
        "InputActionName": "Interact",
        "KeyRelationName": "CButtonA",
        "ActionType": 4
      },
      "InputAction1": {
        "InputActionName": "TriangleR",
        "KeyRelationName": "CButtonB",
        "ActionType": 4
      },
      "InputAction2": {
        "InputActionName": "TriangleL",
        "KeyRelationName": "CButtonX",
        "ActionType": 4
      },
      "InputAction3": {
        "InputActionName": "FinalSkill",
        "KeyRelationName": "CButtonY",
        "ActionType": 4
      },
      "InputAction4": {
        "InputActionName": "RAttack",
        "KeyRelationName": "CButtonRightShoulder",
        "ActionType": 4
      },
      "InputAction5": {
        "InputActionName": "LAttack",
        "KeyRelationName": "CButtonLeftShoulder",
        "ActionType": 4
      },
      "InputAction6": {
        "InputActionName": "LVertical",
        "KeyRelationName": "CLeftY",
        "ActionType": 1
      },
      "InputAction7": {
        "InputActionName": "LHorizontal",
        "KeyRelationName": "CLeftX",
        "ActionType": 1
      },
      "InputAction8": {
        "InputActionName": "RVertical",
        "KeyRelationName": "CRightY",
        "ActionType": 1
      },
      "InputAction9": {
        "InputActionName": "RHorizontal",
        "KeyRelationName": "CRightX",
        "ActionType": 1
      },
      "InputAction10": {
        "InputActionName": "RAllyAttack",
        "KeyRelationName": "CButtonRightStick",
        "ActionType": 4
      },
      "InputAction11": {
        "InputActionName": "LAllyAttack",
        "KeyRelationName": "CButtonLeftStick",
        "ActionType": 4
      }
    }
  }
}