{"Prefab":{"Info":{"Number of GameObjects":4,"Directory Prefab":"","Resources":{"Number of Resources":2,"Type":3,"Resource 0":{"UUID Resource":889498161,"Name":"top_lamp","Type":3},"Resource 1":{"UUID Resource":1118822364,"Name":"top","Type":3}}},"GameObject0":{"UUID":1843585434,"Parent":-1,"Name":"top_lamp.FBX","Tag":"undefined","AnimRotations":true,"AnimScales":false,"AnimTranslations":false,"Number of Components":1,"Components":{"Component 0":{"Component:":"Transform","Type":0,"Position":[0,3.4042768478393555,0],"Rotation":[0,0,0,1],"Scale":[1,1,1]}}},"GameObject1":{"UUID":1758663266,"Parent":1843585434,"Name":"top_lamp","Tag":"undefined","AnimRotations":true,"AnimScales":false,"AnimTranslations":false,"Number of Components":3,"Components":{"Component 0":{"Component:":"Transform","Type":0,"Position":[0.020220771431922913,-0.67603296041488647,-8.0589416029397398e-08],"Rotation":[5.9604644775390625e-08,0,0,1],"Scale":[2.6931250095367432,2.6931250095367432,2.6931250095367432]},"Component 1":{"Component:":"CompMesh","Type":2,"UUID":1286233004,"Resource Mesh UUID":889498161,"Has Skeleton":false,"Generated Skeleton":false},"Component 2":{"Component:":"CompMaterial","Type":3,"Color":[1,1,1,1],"UUID":907375231,"MaterialName:":"lampmaterial"}}},"GameObject2":{"UUID":1266050865,"Parent":1843585434,"Name":"top_cross.FBX","Tag":"undefined","AnimRotations":true,"AnimScales":false,"AnimTranslations":false,"Number of Components":1,"Components":{"Component 0":{"Component:":"Transform","Type":0,"Position":[0,0,0],"Rotation":[0,0,0,1],"Scale":[1,1,1]}}},"GameObject3":{"UUID":2050028430,"Parent":1266050865,"Name":"top","Tag":"undefined","AnimRotations":true,"AnimScales":false,"AnimTranslations":false,"Number of Components":3,"Components":{"Component 0":{"Component:":"Transform","Type":0,"Position":[0,0,0],"Rotation":[-0.70710676908493042,0,0,0.70710676908493042],"Scale":[2.5399999618530273,2.5399999618530273,2.5399999618530273]},"Component 1":{"Component:":"CompMesh","Type":2,"UUID":1708659721,"Resource Mesh UUID":1118822364,"Has Skeleton":false,"Generated Skeleton":false},"Component 2":{"Component:":"CompMaterial","Type":3,"Color":[1,1,1,1],"UUID":889293823,"MaterialName:":"Default Material"}}}}}